amqp-stubs/__init__.pyi
amqp-stubs/abstract_channel.pyi
amqp-stubs/basic_message.pyi
amqp-stubs/channel.pyi
amqp-stubs/connection.pyi
amqp-stubs/exceptions.pyi
amqp-stubs/method_framing.pyi
amqp-stubs/platform.pyi
amqp-stubs/protocol.pyi
amqp-stubs/py.typed
amqp-stubs/sasl.pyi
amqp-stubs/serialization.pyi
amqp-stubs/spec.pyi
amqp-stubs/transport.pyi
amqp-stubs/utils.pyi
billiard-stubs/__init__.pyi
billiard-stubs/allowlist.txt
billiard-stubs/common.pyi
billiard-stubs/compat.pyi
billiard-stubs/connection.pyi
billiard-stubs/context.pyi
billiard-stubs/dummy/__init__.pyi
billiard-stubs/dummy/connection.pyi
billiard-stubs/einfo.pyi
billiard-stubs/exceptions.pyi
billiard-stubs/forkserver.pyi
billiard-stubs/heap.pyi
billiard-stubs/managers.pyi
billiard-stubs/pool.pyi
billiard-stubs/popen_fork.pyi
billiard-stubs/popen_forkserver.pyi
billiard-stubs/popen_spawn_posix.pyi
billiard-stubs/popen_spawn_win32.pyi
billiard-stubs/process.pyi
billiard-stubs/py.typed
billiard-stubs/queues.pyi
billiard-stubs/reduction.pyi
billiard-stubs/resource_sharer.pyi
billiard-stubs/semaphore_tracker.pyi
billiard-stubs/sharedctypes.pyi
billiard-stubs/spawn.pyi
billiard-stubs/synchronize.pyi
billiard-stubs/util.pyi
celery-stubs/__init__.pyi
celery-stubs/__main__.pyi
celery-stubs/_state.pyi
celery-stubs/allowlist.txt
celery-stubs/app/__init__.pyi
celery-stubs/app/amqp.pyi
celery-stubs/app/annotations.pyi
celery-stubs/app/autoretry.pyi
celery-stubs/app/backends.pyi
celery-stubs/app/base.pyi
celery-stubs/app/builtins.pyi
celery-stubs/app/control.pyi
celery-stubs/app/defaults.pyi
celery-stubs/app/events.pyi
celery-stubs/app/log.pyi
celery-stubs/app/registry.pyi
celery-stubs/app/routes.pyi
celery-stubs/app/task.pyi
celery-stubs/app/trace.pyi
celery-stubs/app/utils.pyi
celery-stubs/apps/__init__.pyi
celery-stubs/apps/beat.pyi
celery-stubs/apps/multi.pyi
celery-stubs/apps/worker.pyi
celery-stubs/backends/__init__.pyi
celery-stubs/backends/arangodb.pyi
celery-stubs/backends/asynchronous.pyi
celery_types_ng-0.25.6.dist-info/licenses/LICENSE
celery_types_ng-0.25.6.dist-info/WHEEL
celery_types_ng-0.25.6.dist-info/METADATA
celery_types_ng-0.25.6.dist-info/RECORD
