Metadata-Version: 2.4
Name: celery-types-ng
Version: 0.25.6
Summary: Type stubs for Celery and its related packages
Keywords: celery,kombu,vine,amqp,billiard,django_celery_results,types,mypy,stubs
Author: Steve Dignam
Author-email: Steve Dignam <steve@dignam.xyz>
License-Expression: Apache-2.0
License-File: LICENSE
Classifier: License :: OSI Approved :: Apache Software License
Classifier: Programming Language :: Python :: 3
Classifier: Programming Language :: Python :: 3.10
Classifier: Programming Language :: Python :: 3.11
Classifier: Programming Language :: Python :: 3.12
Classifier: Programming Language :: Python :: 3.13
Classifier: Programming Language :: Python :: 3.14
Classifier: Typing :: Stubs Only
Classifier: Typing :: Typed
Requires-Dist: typing-extensions>=4.15.0,<5
Requires-Python: >=3.10, <4
Project-URL: Repository, https://github.com/sbdchd/celery-types
